{
  "depot": "IBRAHIMPATNAM",
  "target_date": "2026-05-17",
  "predicted_depot_pkm": 1971773.625,
  "total_services": 189,
  "count_add_slot": 129,
  "count_cut": 2,
  "count_no_change": 58,
  "total_allocated_pkm": 1788919.02282836,
  "quadrant_counts": {
    "UNDERSUPPLY": 159,
    "INEFFICIENT": 15,
    "OVERSUPPLY": 15
  },
  "quadrant_pcts": {
    "UNDERSUPPLY": 84.1,
    "INEFFICIENT": 7.9,
    "OVERSUPPLY": 7.9
  },
  "total_revenue": 2373290.177324582,
  "total_contribution": 1494700.0453245821,
  "total_planned_kms": 44778.7,
  "depot_avg_epk": 55.065128754728285,
  "depot_avg_or": 0.9013675764336196,
  "revenue_by_quadrant": {
    "INEFFICIENT": 6103.791068427436,
    "OVERSUPPLY": 111123.15568652001,
    "UNDERSUPPLY": 2256063.2305696346
  },
  "contribution_by_quadrant": {
    "INEFFICIENT": -81558.92893157256,
    "OVERSUPPLY": 36398.96368652002,
    "UNDERSUPPLY": 1539860.0105696344
  }
}