{
  "depot": "KARIMNAGAR-I",
  "target_date": "2026-05-20",
  "predicted_depot_pkm": 1773722.125,
  "total_services": 108,
  "count_add_slot": 26,
  "count_cut": 7,
  "count_no_change": 75,
  "total_allocated_pkm": 1629218.9110615833,
  "quadrant_counts": {
    "UNDERSUPPLY": 74,
    "OVERSUPPLY": 25,
    "INEFFICIENT": 9
  },
  "quadrant_pcts": {
    "UNDERSUPPLY": 68.5,
    "OVERSUPPLY": 23.1,
    "INEFFICIENT": 8.3
  },
  "total_revenue": 2074067.8258467438,
  "total_contribution": 936536.065846744,
  "total_planned_kms": 47350.0,
  "depot_avg_epk": 44.81965831954627,
  "depot_avg_or": 0.7148115882520844,
  "revenue_by_quadrant": {
    "INEFFICIENT": 62246.11941172835,
    "OVERSUPPLY": 471365.58394699154,
    "UNDERSUPPLY": 1540456.122488024
  },
  "contribution_by_quadrant": {
    "INEFFICIENT": -60177.02058827164,
    "OVERSUPPLY": 220833.36394699154,
    "UNDERSUPPLY": 775879.7224880239
  }
}