{
  "depot": "NARKATPALLY",
  "target_date": "2026-06-25",
  "predicted_depot_pkm": 672189.125,
  "total_services": 26,
  "count_add_slot": 4,
  "count_cut": 0,
  "count_add_candidates_no_spare": 2,
  "count_no_change": 20,
  "total_allocated_pkm": 664147.3850056169,
  "quadrant_counts": {
    "UNDERSUPPLY": 26
  },
  "quadrant_pcts": {
    "UNDERSUPPLY": 100.0
  },
  "total_revenue": 744951.6919405079,
  "total_contribution": 486201.6919405078,
  "total_planned_kms": 10350.0,
  "depot_avg_epk": 72.42042258838043,
  "depot_avg_or": 1.168676270532412,
  "revenue_by_quadrant": {
    "UNDERSUPPLY": 744951.6919405079
  },
  "contribution_by_quadrant": {
    "UNDERSUPPLY": 486201.69194050785
  },
  "maintenance_pct": 0.02,
  "pkm_90d_avg": 463031.22910158976,
  "fleet_breakdown": {
    "METRO EXP": {
      "available": 6,
      "planned": 5.0,
      "cut": 0.0,
      "maintenance": 0,
      "spare": 1.0,
      "estimated": true,
      "added": 1,
      "to_add": 1
    },
    "PALLEVELUGU": {
      "available": 24,
      "planned": 21.0,
      "cut": 0.0,
      "maintenance": 0,
      "spare": 3.0,
      "estimated": true,
      "added": 3,
      "to_add": 5
    }
  }
}