{
  "depot": "MEDAK",
  "target_date": "2026-06-21",
  "predicted_depot_pkm": 1730398.375,
  "total_services": 83,
  "count_add_slot": 2,
  "count_cut": 8,
  "count_add_candidates_no_spare": 21,
  "count_no_change": 52,
  "total_allocated_pkm": 1426854.6002431682,
  "quadrant_counts": {
    "UNDERSUPPLY": 58,
    "INEFFICIENT": 15,
    "OVERSUPPLY": 10
  },
  "quadrant_pcts": {
    "UNDERSUPPLY": 69.9,
    "INEFFICIENT": 18.1,
    "OVERSUPPLY": 12.0
  },
  "total_revenue": 1586592.970022559,
  "total_contribution": 783442.970022559,
  "total_planned_kms": 32126.0,
  "depot_avg_epk": 48.54736755620885,
  "depot_avg_or": 0.8025833375515818,
  "revenue_by_quadrant": {
    "INEFFICIENT": 46326.731902671636,
    "OVERSUPPLY": 153113.42638405674,
    "UNDERSUPPLY": 1387152.8117358307
  },
  "contribution_by_quadrant": {
    "INEFFICIENT": -87098.26809732837,
    "OVERSUPPLY": 49638.42638405676,
    "UNDERSUPPLY": 820902.8117358307
  },
  "maintenance_pct": 0.08,
  "pkm_90d_avg": 1736467.285735115,
  "fleet_breakdown": {
    "BB": {
      "available": 10,
      "planned": 9.0,
      "cut": 8.0,
      "maintenance": 1,
      "spare": 8.0,
      "estimated": true,
      "added": 0,
      "to_add": 0
    },
    "EXP": {
      "available": 13,
      "planned": 11.0,
      "cut": 0.0,
      "maintenance": 1,
      "spare": 1.0,
      "estimated": true,
      "added": 0,
      "to_add": 0
    },
    "HEXP": {
      "available": 5,
      "planned": 4.0,
      "cut": 0.0,
      "maintenance": 0,
      "spare": 1.0,
      "estimated": true,
      "added": 1,
      "to_add": 1
    },
    "HPVG": {
      "available": 53,
      "planned": 48.0,
      "cut": 0.0,
      "maintenance": 4,
      "spare": 1.0,
      "estimated": true,
      "added": 1,
      "to_add": 22
    },
    "PVG": {
      "available": 13,
      "planned": 11.0,
      "cut": 0.0,
      "maintenance": 1,
      "spare": 1.0,
      "estimated": true,
      "added": 0,
      "to_add": 0
    }
  }
}