{
  "depot": "FAROOQNAGAR",
  "target_date": "2026-05-08",
  "predicted_depot_pkm": 1135220.75,
  "total_services": 153,
  "count_add_slot": 105,
  "count_cut": 0,
  "count_no_change": 48,
  "total_allocated_pkm": 1090417.3859548895,
  "quadrant_counts": {
    "UNDERSUPPLY": 120,
    "OVERSUPPLY": 17,
    "INEFFICIENT": 16
  },
  "quadrant_pcts": {
    "UNDERSUPPLY": 78.4,
    "OVERSUPPLY": 11.1,
    "INEFFICIENT": 10.5
  },
  "total_revenue": 1501124.5574923474,
  "total_contribution": 860324.5574923474,
  "total_planned_kms": 25632.0,
  "depot_avg_epk": 58.3811962068747,
  "depot_avg_or": 0.926230144071658,
  "revenue_by_quadrant": {
    "INEFFICIENT": 15586.322336533309,
    "OVERSUPPLY": 90672.75016631949,
    "UNDERSUPPLY": 1394865.4849894946
  },
  "contribution_by_quadrant": {
    "INEFFICIENT": -57113.67766346669,
    "OVERSUPPLY": 31672.75016631948,
    "UNDERSUPPLY": 885765.4849894947
  }
}