{
  "depot": "GODAVARIKHANI",
  "target_date": "2026-05-27",
  "predicted_depot_pkm": 1625560.5,
  "total_services": 120,
  "count_add_slot": 8,
  "count_cut": 0,
  "count_no_change": 112,
  "total_allocated_pkm": 1465076.7348384894,
  "quadrant_counts": {
    "OVERSUPPLY": 79,
    "UNDERSUPPLY": 26,
    "INEFFICIENT": 15
  },
  "quadrant_pcts": {
    "OVERSUPPLY": 65.8,
    "UNDERSUPPLY": 21.7,
    "INEFFICIENT": 12.5
  },
  "total_revenue": 1883800.5526544903,
  "total_contribution": 552300.5526544903,
  "total_planned_kms": 53260.0,
  "depot_avg_epk": 36.00771937156053,
  "depot_avg_or": 0.5686889365249835,
  "revenue_by_quadrant": {
    "INEFFICIENT": 91251.48199403983,
    "OVERSUPPLY": 1257593.2445551837,
    "UNDERSUPPLY": 534955.8261052668
  },
  "contribution_by_quadrant": {
    "INEFFICIENT": -100773.51800596017,
    "OVERSUPPLY": 387193.2445551838,
    "UNDERSUPPLY": 265880.82610526675
  }
}