{
  "depot": "MEDCHAL",
  "target_date": "2026-06-22",
  "predicted_depot_pkm": 1999459.375,
  "total_services": 182,
  "count_add_slot": 0,
  "count_cut": 0,
  "count_add_candidates_no_spare": 8,
  "count_no_change": 174,
  "total_allocated_pkm": 1562895.245930977,
  "quadrant_counts": {
    "UNDERSUPPLY": 102,
    "OVERSUPPLY": 41,
    "INEFFICIENT": 39
  },
  "quadrant_pcts": {
    "UNDERSUPPLY": 56.0,
    "OVERSUPPLY": 22.5,
    "INEFFICIENT": 21.4
  },
  "total_revenue": 2179662.465425275,
  "total_contribution": 1077548.9654252746,
  "total_planned_kms": 44084.54,
  "depot_avg_epk": 51.329632346755886,
  "depot_avg_or": 0.7123226501034077,
  "revenue_by_quadrant": {
    "INEFFICIENT": 34622.11172156755,
    "OVERSUPPLY": 366087.6333334436,
    "UNDERSUPPLY": 1778952.7203702633
  },
  "contribution_by_quadrant": {
    "INEFFICIENT": -269452.8882784324,
    "OVERSUPPLY": 161584.3833334436,
    "UNDERSUPPLY": 1185417.4703702633
  },
  "maintenance_pct": 0.02,
  "pkm_90d_avg": 1550887.4189479614,
  "fleet_breakdown": {
    "IH": {
      "available": 4,
      "planned": 4.0,
      "cut": 0.0,
      "maintenance": 0,
      "spare": 0.0,
      "estimated": false,
      "added": 0,
      "to_add": 0
    },
    "ME": {
      "available": 42,
      "planned": 45.0,
      "cut": 0.0,
      "maintenance": 1,
      "spare": -4.0,
      "estimated": false,
      "added": 0,
      "to_add": 8
    },
    "MO": {
      "available": 17,
      "planned": 15.0,
      "cut": 0.0,
      "maintenance": 0,
      "spare": 2.0,
      "estimated": true,
      "added": 0,
      "to_add": 0
    },
    "PM": {
      "available": 8,
      "planned": 7.0,
      "cut": 0.0,
      "maintenance": 0,
      "spare": 1.0,
      "estimated": true,
      "added": 0,
      "to_add": 0
    },
    "PS": {
      "available": 8,
      "planned": 1.0,
      "cut": 0.0,
      "maintenance": 0,
      "spare": 7.0,
      "estimated": false,
      "added": 0,
      "to_add": 0
    },
    "SU": {
      "available": 5,
      "planned": 4.0,
      "cut": 0.0,
      "maintenance": 0,
      "spare": 1.0,
      "estimated": true,
      "added": 0,
      "to_add": 0
    },
    "VR": {
      "available": 14,
      "planned": 14.0,
      "cut": 0.0,
      "maintenance": 0,
      "spare": 0.0,
      "estimated": false,
      "added": 0,
      "to_add": 0
    },
    "XS": {
      "available": 79,
      "planned": 39.0,
      "cut": 0.0,
      "maintenance": 2,
      "spare": 38.0,
      "estimated": false,
      "added": 0,
      "to_add": 0
    }
  }
}