{
  "depot": "CONTONMENT",
  "target_date": "2026-05-04",
  "predicted_depot_pkm": 2026020.0,
  "total_services": 280,
  "count_add_slot": 161,
  "count_cut": 0,
  "count_no_change": 119,
  "total_allocated_pkm": 1540582.8941961543,
  "quadrant_counts": {
    "UNDERSUPPLY": 181,
    "INEFFICIENT": 50,
    "OVERSUPPLY": 46,
    "SOCIAL_OBLIGATION": 3
  },
  "quadrant_pcts": {
    "UNDERSUPPLY": 64.6,
    "INEFFICIENT": 17.9,
    "OVERSUPPLY": 16.4,
    "SOCIAL_OBLIGATION": 1.1
  },
  "total_revenue": 2513509.9670637483,
  "total_contribution": 1052738.9056637483,
  "total_planned_kms": 46115.74,
  "depot_avg_epk": 59.50197752863223,
  "depot_avg_or": 0.9329084138278566,
  "revenue_by_quadrant": {
    "INEFFICIENT": 74261.36263424964,
    "OVERSUPPLY": 335229.70688579674,
    "SOCIAL_OBLIGATION": 20502.508666335798,
    "UNDERSUPPLY": 2083516.3888773657
  },
  "contribution_by_quadrant": {
    "INEFFICIENT": -304620.4423657503,
    "OVERSUPPLY": 104731.89008579675,
    "SOCIAL_OBLIGATION": -966.8113336642018,
    "UNDERSUPPLY": 1253594.2692773659
  }
}