{
  "depot": "GODAVARIKHANI",
  "target_date": "2026-06-18",
  "predicted_depot_pkm": 2038558.125,
  "total_services": 120,
  "count_add_slot": 1,
  "count_cut": 0,
  "count_add_candidates_no_spare": 0,
  "count_no_change": 119,
  "total_allocated_pkm": 1803030.8640891116,
  "quadrant_counts": {
    "UNDERSUPPLY": 63,
    "OVERSUPPLY": 45,
    "INEFFICIENT": 12
  },
  "quadrant_pcts": {
    "UNDERSUPPLY": 52.5,
    "OVERSUPPLY": 37.5,
    "INEFFICIENT": 10.0
  },
  "total_revenue": 2319940.7737934478,
  "total_contribution": 988440.7737934474,
  "total_planned_kms": 53260.0,
  "depot_avg_epk": 44.47217994819859,
  "depot_avg_or": 0.7005083698027558,
  "revenue_by_quadrant": {
    "INEFFICIENT": 59593.378436064064,
    "OVERSUPPLY": 819569.9601673643,
    "UNDERSUPPLY": 1440777.435190019
  },
  "contribution_by_quadrant": {
    "INEFFICIENT": -93831.62156393593,
    "OVERSUPPLY": 290219.96016736433,
    "UNDERSUPPLY": 792052.435190019
  },
  "maintenance_pct": 0.08,
  "pkm_90d_avg": 2068587.5552764232,
  "fleet_breakdown": {
    "AH": {
      "available": 2,
      "planned": 2.0,
      "cut": 0.0,
      "maintenance": 0,
      "spare": 0.0,
      "estimated": false,
      "added": 0,
      "to_add": 0
    },
    "EX": {
      "available": 12,
      "planned": 6.0,
      "cut": 0.0,
      "maintenance": 1,
      "spare": 5.0,
      "estimated": false,
      "added": 0,
      "to_add": 0
    },
    "HT": {
      "available": 21,
      "planned": 18.0,
      "cut": 0.0,
      "maintenance": 2,
      "spare": 1.0,
      "estimated": false,
      "added": 0,
      "to_add": 0
    },
    "IH": {
      "available": 3,
      "planned": 2.0,
      "cut": 0.0,
      "maintenance": 0,
      "spare": 1.0,
      "estimated": true,
      "added": 0,
      "to_add": 0
    },
    "JC": {
      "available": 15,
      "planned": 14.0,
      "cut": 0.0,
      "maintenance": 1,
      "spare": 0.0,
      "estimated": false,
      "added": 0,
      "to_add": 0
    },
    "MB": {
      "available": 7,
      "planned": 5.0,
      "cut": 0.0,
      "maintenance": 1,
      "spare": 1.0,
      "estimated": false,
      "added": 0,
      "to_add": 0
    },
    "OR": {
      "available": 30,
      "planned": 27.0,
      "cut": 0.0,
      "maintenance": 2,
      "spare": 1.0,
      "estimated": false,
      "added": 1,
      "to_add": 1
    },
    "PE": {
      "available": 13,
      "planned": 13.0,
      "cut": 0.0,
      "maintenance": 1,
      "spare": -1.0,
      "estimated": false,
      "added": 0,
      "to_add": 0
    },
    "PO": {
      "available": 27,
      "planned": 27.0,
      "cut": 0.0,
      "maintenance": 2,
      "spare": -2.0,
      "estimated": false,
      "added": 0,
      "to_add": 0
    }
  }
}